yasca/__init__.py
yasca/main.py
yasca/utils.py
yasca/data/queries.yaml
yasca/maven_scanner/__init__.py
yasca/maven_scanner/maven_scanner.py
yasca/maven_scanner/maven_tree_generator.py
yasca/template/cyclonedx_template.json
yasca/template/report_template.html
yasca-1.0.0.dist-info/LICENSE
yasca-1.0.0.dist-info/METADATA
yasca-1.0.0.dist-info/WHEEL
yasca-1.0.0.dist-info/entry_points.txt
yasca-1.0.0.dist-info/top_level.txt
yasca-1.0.0.dist-info/RECORD
